estatpandas/__init__.py
estatpandas/estat_data.py
estatpandas-0.1.0.dist-info/LICENSE
estatpandas-0.1.0.dist-info/METADATA
estatpandas-0.1.0.dist-info/WHEEL
estatpandas-0.1.0.dist-info/top_level.txt
estatpandas-0.1.0.dist-info/RECORD
