Metadata-Version: 2.1
Name: estatpandas
Version: 0.1.0
Summary: A simple package to fetch e-stat data and convert it to a pandas DataFrame
Home-page: https://github.com/yourusername/estatpandas
Author: Shun Nakayama
Author-email: shun-nakayama@keio.jp
Classifier: Development Status :: 3 - Alpha
Classifier: License :: OSI Approved :: MIT License
Classifier: Programming Language :: Python :: 3
Classifier: Programming Language :: Python :: 3.6
Classifier: Programming Language :: Python :: 3.7
Classifier: Programming Language :: Python :: 3.8
Classifier: Programming Language :: Python :: 3.9
License-File: LICENSE
Requires-Dist: requests
Requires-Dist: pandas
